ioflo/__init__.py
ioflo/__metadata__.py
ioflo/__metadata__oldpython.py
ioflo/aid/__init__.py
ioflo/aid/aiding.py
ioflo/aid/blending.py
ioflo/aid/byting.py
ioflo/aid/checking.py
ioflo/aid/classing.py
ioflo/aid/consoling.py
ioflo/aid/eventing.py
ioflo/aid/filing.py
ioflo/aid/navigating.py
ioflo/aid/odicting.py
ioflo/aid/optimizing.py
ioflo/aid/osetting.py
ioflo/aid/quaternioning.py
ioflo/aid/sixing.py
ioflo/aid/timing.py
ioflo/aid/vectoring.py
ioflo/aid/test/__init__.py
ioflo/aid/test/test_aiding.py
ioflo/aid/test/test_blending.py
ioflo/aid/test/test_byting.py
ioflo/aid/test/test_classing.py
ioflo/aid/test/test_eventing.py
ioflo/aid/test/test_odicting.py
ioflo/aid/test/test_osetting.py
ioflo/aid/test/test_quating.py
ioflo/aid/test/test_sixing.py
ioflo/aid/test/test_timing.py
ioflo/aid/test/test_vectoring.py
ioflo/aio/__init__.py
ioflo/aio/aioing.py
ioflo/aio/wiring.py
ioflo/aio/http/__init__.py
ioflo/aio/http/clienting.py
ioflo/aio/http/httping.py
ioflo/aio/http/serving.py
ioflo/aio/http/test/__init__.py
ioflo/aio/http/test/test_clienting.py
ioflo/aio/http/test/test_serving.py
ioflo/aio/proto/__init__.py
ioflo/aio/proto/devicing.py
ioflo/aio/proto/exchanging.py
ioflo/aio/proto/packeting.py
ioflo/aio/proto/protoing.py
ioflo/aio/proto/stacking.py
ioflo/aio/proto/test/__init__.py
ioflo/aio/proto/test/test_devicing.py
ioflo/aio/proto/test/test_exchanging.py
ioflo/aio/proto/test/test_packeting.py
ioflo/aio/proto/test/test_stacking.py
ioflo/aio/serial/__init__.py
ioflo/aio/serial/serialing.py
ioflo/aio/serial/test/__init__.py
ioflo/aio/serial/test/test_serialing.py
ioflo/aio/tcp/__init__.py
ioflo/aio/tcp/clienting.py
ioflo/aio/tcp/serving.py
ioflo/aio/tcp/test/__init__.py
ioflo/aio/tcp/test/test_tcping.py
ioflo/aio/test/__init__.py
ioflo/aio/test/_test_httping_w_ext_server.py
ioflo/aio/test/_test_tls_w_ext_serverclient.py
ioflo/aio/test/test_aioing.py
ioflo/aio/test/test_wiring.py
ioflo_py_multiversion_dev-1.7.10.dist-info/DESCRIPTION.rst
ioflo_py_multiversion_dev-1.7.10.dist-info/METADATA
ioflo_py_multiversion_dev-1.7.10.dist-info/RECORD
ioflo_py_multiversion_dev-1.7.10.dist-info/WHEEL
ioflo_py_multiversion_dev-1.7.10.dist-info/metadata.json
ioflo_py_multiversion_dev-1.7.10.dist-info/top_level.txt
